<?xml version="1.0" encoding="utf-8"?>
<edmx:Edmx Version="4.0" xmlns:edmx="http://docs.oasis-open.org/odata/ns/edmx">
    <edmx:Reference Uri="../../catalogservice;v=2/Vocabularies(TechnicalName='%2FIWBEP%2FVOC_COMMON',Version='0001',SAP__Origin='')/$value">
        <edmx:Include Namespace="com.sap.vocabularies.Common.v1" Alias="Common"/>
    </edmx:Reference>
    <edmx:Reference Uri="../../catalogservice;v=2/Vocabularies(TechnicalName='%2FIWBEP%2FVOC_UI',Version='0001',SAP__Origin='')/$value">
        <edmx:Include Namespace="com.sap.vocabularies.UI.v1" Alias="UI"/>
    </edmx:Reference>
    <edmx:Reference Uri="../../catalogservice;v=2/Vocabularies(TechnicalName='%2FIWBEP%2FVOC_COMMUNICATION',Version='0001',SAP__Origin='')/$value">
        <edmx:Include Namespace="com.sap.vocabularies.Communication.v1" Alias="Communication"/>
    </edmx:Reference>
    <edmx:Reference Uri="../../catalogservice;v=2/Vocabularies(TechnicalName='%2FIWBEP%2FVOC_PERSONALDATA',Version='0001',SAP__Origin='')/$value">
        <edmx:Include Namespace="com.sap.vocabularies.PersonalData.v1" Alias="PersonalData"/>
    </edmx:Reference>
    <edmx:Reference Uri="../../catalogservice;v=2/Vocabularies(TechnicalName='%2FIWBEP%2FVOC_VALIDATION',Version='0001',SAP__Origin='')/$value">
        <edmx:Include Namespace="Org.OData.Validation.V1" Alias="Validation"/>
    </edmx:Reference>
    <edmx:Reference Uri="../../catalogservice;v=2/Vocabularies(TechnicalName='%2FIWBEP%2FVOC_ANALYTICS',Version='0001',SAP__Origin='')/$value">
        <edmx:Include Namespace="com.sap.vocabularies.Analytics.v1" Alias="Analytics"/>
    </edmx:Reference>
    <edmx:Reference Uri="../../catalogservice;v=2/Vocabularies(TechnicalName='%2FIWBEP%2FVOC_HTML5',Version='0001',SAP__Origin='')/$value">
        <edmx:Include Namespace="com.sap.vocabularies.HTML5.v1" Alias="HTML5"/>
    </edmx:Reference>
    <edmx:Reference Uri="../../../sap/zmrbs_ui2_apl/$metadata">
        <edmx:Include Namespace="ZMRBS_UI2_APL" Alias="SAP"/>
    </edmx:Reference>
    <edmx:DataServices>
        <Schema Namespace="zmrbs_ui2_apl_van.v1" xmlns="http://docs.oasis-open.org/odata/ns/edm">
            <Annotations Target="cds_zmrbs_ui_apl.BookingAnalysisSetType/ID">
                <Annotation Term="UI.Hidden"/>
            </Annotations>
            <Annotations Target="cds_zmrbs_ui_apl.BookingAnalysisSetType">
                <Annotation Term="UI.Chart" Qualifier="visualDate">
                    <Record Type="UI.ChartDefinitionType">
                        <PropertyValue Property="Description" String="Booking Data"/>
                        <PropertyValue Property="ChartType" EnumMember="UI.ChartType/Bar"/>
                        <PropertyValue Property="Dimensions">
                            <Collection>
                                <PropertyPath>monYr</PropertyPath>
                            </Collection>
                        </PropertyValue>
                        <PropertyValue Property="DimensionAttributes">
                            <Collection>
                                <Record Type="UI.ChartDimensionAttributeType">
                                    <PropertyValue Property="Dimension" PropertyPath="monYr"/>
                                    <PropertyValue Property="Role" EnumMember="UI.ChartDimensionRoleType/Category"/>
                                </Record>
                            </Collection>
                        </PropertyValue>
                        <PropertyValue Property="Measures">
                            <Collection>
                                <PropertyPath>Duration</PropertyPath>
                            </Collection>
                        </PropertyValue>
                        <PropertyValue Property="MeasureAttributes">
                            <Collection>
                                <Record Type="UI.ChartMeasureAttributeType">
                                    <PropertyValue Property="Measure" PropertyPath="Duration"/>
                                    <PropertyValue Property="Role" EnumMember="UI.ChartMeasureRoleType/Axis1"/>
                                </Record>
                            </Collection>
                        </PropertyValue>
                    </Record>
                </Annotation>
                <Annotation Term="UI.Chart" Qualifier="chartDefault">
                    <Record Type="UI.ChartDefinitionType">
                        <PropertyValue Property="Description" String="Booking Information"/>
                        <PropertyValue Property="ChartType" EnumMember="UI.ChartType/Column"/>
                        <PropertyValue Property="Dimensions">
                            <Collection>
                                <PropertyPath>Room</PropertyPath>
                            </Collection>
                        </PropertyValue>
                        <PropertyValue Property="DimensionAttributes">
                            <Collection>
                                <Record Type="UI.ChartDimensionAttributeType">
                                    <PropertyValue Property="Dimension" PropertyPath="Room"/>
                                    <PropertyValue Property="Role" EnumMember="UI.ChartDimensionRoleType/Series"/>
                                </Record>
                            </Collection>
                        </PropertyValue>
                        <PropertyValue Property="Measures">
                            <Collection>
                                <PropertyPath>Duration</PropertyPath>
                            </Collection>
                        </PropertyValue>
                        <PropertyValue Property="MeasureAttributes">
                            <Collection>
                                <Record Type="UI.ChartMeasureAttributeType">
                                    <PropertyValue Property="Measure" PropertyPath="Duration"/>
                                    <PropertyValue Property="Role" EnumMember="UI.ChartMeasureRoleType/Axis1"/>
                                </Record>
                            </Collection>
                        </PropertyValue>
                    </Record>
                </Annotation>
                <Annotation Term="UI.Facets">
                    <Collection>
                        <Record Type="UI.ReferenceFacet">
                            <PropertyValue Property="Label" String="General Information"/>
                            <PropertyValue Property="ID" String="idIdentification"/>
                            <PropertyValue Property="Target" AnnotationPath="@UI.Identification"/>
                        </Record>
                        <Record Type="UI.ReferenceFacet">
                            <PropertyValue Property="Label" String="Booker Information"/>
                            <PropertyValue Property="ID" String="idBookerInfo"/>
                            <PropertyValue Property="Target" AnnotationPath="@UI.FieldGroup#BookerInfo"/>
                        </Record>
                        <Record Type="UI.ReferenceFacet">
                            <PropertyValue Property="Label" String="Date/Time"/>
                            <PropertyValue Property="ID" String="idDatTimInfo"/>
                            <PropertyValue Property="Target" AnnotationPath="@UI.FieldGroup#DateTime"/>
                        </Record>
                    </Collection>
                </Annotation>
                <Annotation Term="UI.FieldGroup" Qualifier="BookerInfo">
                    <Record>
                        <PropertyValue Property="Data">
                            <Collection>
                                <Record Type="UI.DataField">
                                    <PropertyValue Property="Label" String="Booker ID"/>
                                    <PropertyValue Property="Value" Path="booker"/>
                                </Record>
                                <Record Type="UI.DataField">
                                    <PropertyValue Property="Label" String="Booker Full Name"/>
                                    <PropertyValue Property="Value" Path="Name"/>
                                </Record>
                                <Record Type="UI.DataField">
                                    <PropertyValue Property="Label" String="Booker Email"/>
                                    <PropertyValue Property="Value" Path="Email"/>
                                </Record>
                            </Collection>
                        </PropertyValue>
                    </Record>
                </Annotation>
                <Annotation Term="UI.FieldGroup" Qualifier="DateTime">
                    <Record>
                        <PropertyValue Property="Data">
                            <Collection>
                                <Record Type="UI.DataField">
                                    <PropertyValue Property="Label" String="Booking Date"/>
                                    <PropertyValue Property="Value" Path="date_scheduled"/>
                                </Record>
                                <Record Type="UI.DataField">
                                    <PropertyValue Property="Label" String="Month Year"/>
                                    <PropertyValue Property="Value" Path="monYr"/>
                                </Record>
                                <Record Type="UI.DataField">
                                    <PropertyValue Property="Label" String="Start Time"/>
                                    <PropertyValue Property="Value" Path="Start_Time"/>
                                </Record>
                                <Record Type="UI.DataField">
                                    <PropertyValue Property="Label" String="End Time"/>
                                    <PropertyValue Property="Value" Path="End_Time"/>
                                </Record>
                                <Record Type="UI.DataField">
                                    <PropertyValue Property="Label" String="Duration(s)"/>
                                    <PropertyValue Property="Value" Path="Duration"/>
                                </Record>
                            </Collection>
                        </PropertyValue>
                    </Record>
                </Annotation>
                <Annotation Term="UI.HeaderInfo">
                    <Record>
                        <PropertyValue Property="TypeName" String="Booking"/>
                        <PropertyValue Property="TypeNamePlural" String="Bookings"/>
                        <PropertyValue Property="Title">
                            <Record Type="UI.DataField">
                                <PropertyValue Property="Value" Path="Booking"/>
                            </Record>
                        </PropertyValue>
                    </Record>
                </Annotation>
                <Annotation Term="UI.Identification">
                    <Collection>
                        <Record Type="UI.DataField">
                            <PropertyValue Property="Value" Path="Booking"/>
                        </Record>
                        <Record Type="UI.DataField">
                            <PropertyValue Property="Value" Path="Room"/>
                        </Record>
                        <Record Type="UI.DataField">
                            <PropertyValue Property="Value" Path="Title"/>
                        </Record>
                        <Record Type="UI.DataField">
                            <PropertyValue Property="Value" Path="Site"/>
                        </Record>
                    </Collection>
                </Annotation>
                <Annotation Term="UI.LineItem">
                    <Collection>
                        <Record Type="UI.DataField">
                            <PropertyValue Property="Value" Path="Booking"/>
                        </Record>
                        <Record Type="UI.DataField">
                            <PropertyValue Property="Value" Path="Room"/>
                        </Record>
                        <Record Type="UI.DataField">
                            <PropertyValue Property="Value" Path="date_scheduled"/>
                        </Record>
                        <Record Type="UI.DataField">
                            <PropertyValue Property="Value" Path="booker"/>
                        </Record>
                        <Record Type="UI.DataField">
                            <PropertyValue Property="Value" Path="Name"/>
                        </Record>
                        <Record Type="UI.DataField">
                            <PropertyValue Property="Value" Path="Title"/>
                        </Record>
                        <Record Type="UI.DataField">
                            <PropertyValue Property="Value" Path="Site"/>
                        </Record>
                        <Record Type="UI.DataField">
                            <PropertyValue Property="Value" Path="Duration"/>
                        </Record>
                    </Collection>
                </Annotation>
                <Annotation Term="UI.PresentationVariant" Qualifier="visualDate">
                    <Record>
                        <PropertyValue Property="Visualizations">
                            <Collection>
                                <AnnotationPath>@UI.DataPoint#Duration</AnnotationPath>
                                <AnnotationPath>@UI.Chart#visualDate</AnnotationPath>
                            </Collection>
                        </PropertyValue>
                    </Record>
                </Annotation>
                <Annotation Term="UI.PresentationVariant" Qualifier="Default">
                    <Record>
                        <PropertyValue Property="Visualizations">
                            <Collection>
                                <AnnotationPath>@UI.Chart#chartDefault</AnnotationPath>
                            </Collection>
                        </PropertyValue>
                    </Record>
                </Annotation>
                <Annotation Term="UI.SelectionFields">
                    <Collection>
                        <PropertyPath>Booking</PropertyPath>
                        <PropertyPath>date_scheduled</PropertyPath>
                        <PropertyPath>monYr</PropertyPath>
                        <PropertyPath>Site</PropertyPath>
                    </Collection>
                </Annotation>
                <Annotation Term="UI.SelectionPresentationVariant" Qualifier="visualDate">
                    <Record>
                        <PropertyValue Property="Text" String=""/>
                        <PropertyValue Property="SelectionVariant" Path="@UI.SelectionVariant#visualDate"/>
                        <PropertyValue Property="PresentationVariant" Path="@UI.PresentationVariant#visualDate"/>
                    </Record>
                </Annotation>
                <Annotation Term="UI.SelectionVariant" Qualifier="visualDate">
                    <Record>
                        <PropertyValue Property="Text" String=""/>
                    </Record>
                </Annotation>
            </Annotations>
        </Schema>
    </edmx:DataServices>
</edmx:Edmx>